h2lib_tests/__init__.py
h2lib_tests/conftest.py
h2lib_tests/dtu10mw.py
h2lib_tests/test_calc.py
h2lib_tests/test_distributed_sections.py
h2lib_tests/test_ellipsys_couplings.py
h2lib_tests/test_h2lib.py
h2lib_tests/test_h2rotor.py
h2lib_tests/test_lin.py
h2lib_tests/test_mpi.py
h2lib_tests/test_multiprocessinterface.py
h2lib_tests/test_static_solver.py
h2lib_tests/test_topology_h2lib.py
h2lib_tests/test_files/__init__.py
h2lib_tests/test_files/my_test_cls.py
h2lib_tests/test_files/DTU_10_MW/control/dtu_we_controller.dll
h2lib_tests/test_files/DTU_10_MW/control/dtu_we_controller.so
h2lib_tests/test_files/DTU_10_MW/control/dtu_we_controller_64.dll
h2lib_tests/test_files/DTU_10_MW/control/generator_servo.dll
h2lib_tests/test_files/DTU_10_MW/control/generator_servo.so
h2lib_tests/test_files/DTU_10_MW/control/generator_servo_64.dll
h2lib_tests/test_files/DTU_10_MW/control/mech_brake.dll
h2lib_tests/test_files/DTU_10_MW/control/mech_brake.so
h2lib_tests/test_files/DTU_10_MW/control/mech_brake_64.dll
h2lib_tests/test_files/DTU_10_MW/control/servo_with_limits.dll
h2lib_tests/test_files/DTU_10_MW/control/servo_with_limits.so
h2lib_tests/test_files/DTU_10_MW/control/servo_with_limits2.dll
h2lib_tests/test_files/DTU_10_MW/control/servo_with_limits2.so
h2lib_tests/test_files/DTU_10_MW/control/servo_with_limits2_64.dll
h2lib_tests/test_files/DTU_10_MW/control/servo_with_limits_64.dll
h2lib_tests/test_files/DTU_10_MW/control/towerclearance_mblade.dll
h2lib_tests/test_files/DTU_10_MW/control/towerclearance_mblade.so
h2lib_tests/test_files/DTU_10_MW/control/towerclearance_mblade_64.dll
h2lib_tests/test_files/DTU_10_MW/control/wpdata.100
h2lib_tests/test_files/DTU_10_MW/data/DTU_10MW_RWT_Blade_st.dat
h2lib_tests/test_files/DTU_10_MW/data/DTU_10MW_RWT_Hub_st.dat
h2lib_tests/test_files/DTU_10_MW/data/DTU_10MW_RWT_Shaft_st.dat
h2lib_tests/test_files/DTU_10_MW/data/DTU_10MW_RWT_Tower_st.dat
h2lib_tests/test_files/DTU_10_MW/data/DTU_10MW_RWT_Tower_st.dat.v3.enc
h2lib_tests-13.2.901.dist-info/METADATA
h2lib_tests-13.2.901.dist-info/WHEEL
h2lib_tests-13.2.901.dist-info/top_level.txt
h2lib_tests-13.2.901.dist-info/RECORD
