Metadata-Version: 2.4
Name: h2lib-tests
Version: 13.2.901
Summary: Tests and test_files for test h2lib (13.2.9+4-gfd77867)
Download-URL: 
Author: Mads M Pedersen
Author-email: 
Maintainer: 
Maintainer-email: 
Requires-Dist: numpy
Requires-Dist: pytest
Requires-Dist: pytest-cov
Requires-Dist: hipersim
Requires-Dist: wetb
Requires-Dist: h2lib
Requires-Dist: Hawc2Models==0.0.4
Dynamic: author
Dynamic: requires-dist
Dynamic: summary
